poetry_aws_lambda_plugin/__init__.py
poetry_aws_lambda_plugin/builders/__init__.py
poetry_aws_lambda_plugin/builders/builder.py
poetry_aws_lambda_plugin/builders/zip.py
poetry_aws_lambda_plugin/commands/__init__.py
poetry_aws_lambda_plugin/commands/build_aws_lambda.py
poetry_aws_lambda_plugin/packages_getters/__init__.py
poetry_aws_lambda_plugin/packages_getters/dependencies.py
poetry_aws_lambda_plugin/packages_getters/package_getter.py
poetry_aws_lambda_plugin/packages_getters/project.py
poetry_aws_lambda_plugin/plugin.py
poetry_aws_lambda_plugin/publishers/__init__.py
poetry_aws_lambda_plugin/publishers/publisher.py
poetry_aws_lambda_plugin/publishers/s3.py
poetry_aws_lambda_plugin/slimmers/__init__.py
poetry_aws_lambda_plugin/slimmers/files_remover.py
poetry_aws_lambda_plugin/slimmers/slimmer.py
poetry_aws_lambda_plugin/steps/__init__.py
poetry_aws_lambda_plugin/steps/step.py
poetry_aws_lambda_plugin/utils/__init__.py
poetry_aws_lambda_plugin/utils/config.py
poetry_aws_lambda_plugin/utils/enums.py
poetry_aws_lambda_plugin/utils/exceptions.py
poetry_aws_lambda_plugin/utils/logging.py
poetry_aws_lambda_plugin-0.2.0.dist-info/entry_points.txt
poetry_aws_lambda_plugin-0.2.0.dist-info/LICENSE
poetry_aws_lambda_plugin-0.2.0.dist-info/METADATA
poetry_aws_lambda_plugin-0.2.0.dist-info/WHEEL
poetry_aws_lambda_plugin-0.2.0.dist-info/RECORD
